synthwave/__init__.py
synthwave/__main__.py
synthwave/data.json
synthwave/event.py
synthwave/field.py
synthwave/schema.py
synthwave/stream.py
synthwave/utils.py
synthwave-0.1.7.dist-info/LICENSE.md
synthwave-0.1.7.dist-info/METADATA
synthwave-0.1.7.dist-info/WHEEL
synthwave-0.1.7.dist-info/RECORD
