Metadata-Version: 2.1
Name: synthwave
Version: 0.1.7
Summary: 
Home-page: https://mcleonard.github.io/synthwave/html/index.html
License: BSD 3-Clause
Author: Mat Leonard
Author-email: leonard.mat@gmail.com
Requires-Python: >=3.11,<4.0
Classifier: License :: Other/Proprietary License
Classifier: Programming Language :: Python :: 3
Classifier: Programming Language :: Python :: 3.11
Requires-Dist: requests (>=2.31.0,<3.0.0)
Requires-Dist: validators (>=0.20.0,<0.21.0)
Project-URL: Repository, https://github.com/mcleonard/synthwave
